CHANGELOG.txt
LICENCE.txt
MANIFEST.in
README.txt
__init__.py
calculator.py
requirements.txt
setup.py
malekbasiccalculator.egg-info/PKG-INFO
malekbasiccalculator.egg-info/SOURCES.txt
malekbasiccalculator.egg-info/dependency_links.txt
malekbasiccalculator.egg-info/requires.txt
malekbasiccalculator.egg-info/top_level.txt
tests/__init__.py
tests/unit/__init__.py
tests/unit/test_calculator.py
venv/bin/activate_this.py
venv/bin/rst2html.py
venv/bin/rst2html4.py
venv/bin/rst2html5.py
venv/bin/rst2latex.py
venv/bin/rst2man.py
venv/bin/rst2odt.py
venv/bin/rst2odt_prepstyles.py
venv/bin/rst2pseudoxml.py
venv/bin/rst2s5.py
venv/bin/rst2xetex.py
venv/bin/rst2xml.py
venv/bin/rstpep2html.py
venv/lib/python3.6/__future__.py
venv/lib/python3.6/_bootlocale.py
venv/lib/python3.6/_collections_abc.py
venv/lib/python3.6/_dummy_thread.py
venv/lib/python3.6/_weakrefset.py
venv/lib/python3.6/abc.py
venv/lib/python3.6/base64.py
venv/lib/python3.6/bisect.py
venv/lib/python3.6/codecs.py
venv/lib/python3.6/copy.py
venv/lib/python3.6/copyreg.py
venv/lib/python3.6/enum.py
venv/lib/python3.6/fnmatch.py
venv/lib/python3.6/functools.py
venv/lib/python3.6/genericpath.py
venv/lib/python3.6/hashlib.py
venv/lib/python3.6/heapq.py
venv/lib/python3.6/hmac.py
venv/lib/python3.6/imp.py
venv/lib/python3.6/io.py
venv/lib/python3.6/keyword.py
venv/lib/python3.6/linecache.py
venv/lib/python3.6/locale.py
venv/lib/python3.6/no-global-site-packages.txt
venv/lib/python3.6/ntpath.py
venv/lib/python3.6/operator.py
venv/lib/python3.6/orig-prefix.txt
venv/lib/python3.6/os.py
venv/lib/python3.6/posixpath.py
venv/lib/python3.6/random.py
venv/lib/python3.6/re.py
venv/lib/python3.6/reprlib.py
venv/lib/python3.6/rlcompleter.py
venv/lib/python3.6/shutil.py
venv/lib/python3.6/site.py
venv/lib/python3.6/sre_compile.py
venv/lib/python3.6/sre_constants.py
venv/lib/python3.6/sre_parse.py
venv/lib/python3.6/stat.py
venv/lib/python3.6/struct.py
venv/lib/python3.6/tarfile.py
venv/lib/python3.6/tempfile.py
venv/lib/python3.6/token.py
venv/lib/python3.6/tokenize.py
venv/lib/python3.6/types.py
venv/lib/python3.6/warnings.py
venv/lib/python3.6/weakref.py
venv/lib/python3.6/collections/__init__.py
venv/lib/python3.6/collections/abc.py
venv/lib/python3.6/site-packages/Flask-1.1.2.dist-info/entry_points.txt
venv/lib/python3.6/site-packages/Flask-1.1.2.dist-info/top_level.txt
venv/lib/python3.6/site-packages/Jinja2-2.11.2.dist-info/entry_points.txt
venv/lib/python3.6/site-packages/Jinja2-2.11.2.dist-info/top_level.txt
venv/lib/python3.6/site-packages/MarkupSafe-1.1.1.dist-info/LICENSE.txt
venv/lib/python3.6/site-packages/MarkupSafe-1.1.1.dist-info/top_level.txt
venv/lib/python3.6/site-packages/Pygments-2.6.1.dist-info/entry_points.txt
venv/lib/python3.6/site-packages/Pygments-2.6.1.dist-info/top_level.txt
venv/lib/python3.6/site-packages/SecretStorage-3.1.2.dist-info/top_level.txt
venv/lib/python3.6/site-packages/Werkzeug-1.0.1.dist-info/top_level.txt
venv/lib/python3.6/site-packages/bleach-3.1.5.dist-info/top_level.txt
venv/lib/python3.6/site-packages/bleach/_vendor/html5lib-1.0.1.dist-info/LICENSE.txt
venv/lib/python3.6/site-packages/bleach/_vendor/html5lib-1.0.1.dist-info/top_level.txt
venv/lib/python3.6/site-packages/certifi-2020.4.5.2.dist-info/top_level.txt
venv/lib/python3.6/site-packages/cffi-1.14.0.dist-info/LICENSE.txt
venv/lib/python3.6/site-packages/cffi-1.14.0.dist-info/entry_points.txt
venv/lib/python3.6/site-packages/cffi-1.14.0.dist-info/top_level.txt
venv/lib/python3.6/site-packages/chardet-3.0.4.dist-info/entry_points.txt
venv/lib/python3.6/site-packages/chardet-3.0.4.dist-info/top_level.txt
venv/lib/python3.6/site-packages/click-7.1.2.dist-info/top_level.txt
venv/lib/python3.6/site-packages/cryptography-2.9.2.dist-info/top_level.txt
venv/lib/python3.6/site-packages/docutils-0.16.dist-info/COPYING.txt
venv/lib/python3.6/site-packages/docutils-0.16.dist-info/top_level.txt
venv/lib/python3.6/site-packages/idna-2.9.dist-info/top_level.txt
venv/lib/python3.6/site-packages/importlib_metadata-1.6.1.dist-info/top_level.txt
venv/lib/python3.6/site-packages/itsdangerous-1.1.0.dist-info/top_level.txt
venv/lib/python3.6/site-packages/keyring-21.2.1.dist-info/entry_points.txt
venv/lib/python3.6/site-packages/keyring-21.2.1.dist-info/top_level.txt
venv/lib/python3.6/site-packages/packaging-20.4.dist-info/top_level.txt
venv/lib/python3.6/site-packages/pip-20.1.1.dist-info/LICENSE.txt
venv/lib/python3.6/site-packages/pip-20.1.1.dist-info/entry_points.txt
venv/lib/python3.6/site-packages/pip-20.1.1.dist-info/top_level.txt
venv/lib/python3.6/site-packages/pkginfo-1.5.0.1.dist-info/LICENSE.txt
venv/lib/python3.6/site-packages/pkginfo-1.5.0.1.dist-info/entry_points.txt
venv/lib/python3.6/site-packages/pkginfo-1.5.0.1.dist-info/top_level.txt
venv/lib/python3.6/site-packages/pycparser-2.20.dist-info/top_level.txt
venv/lib/python3.6/site-packages/pyparsing-2.4.7.dist-info/top_level.txt
venv/lib/python3.6/site-packages/readme_renderer-26.0.dist-info/entry_points.txt
venv/lib/python3.6/site-packages/readme_renderer-26.0.dist-info/top_level.txt
venv/lib/python3.6/site-packages/requests-2.23.0.dist-info/top_level.txt
venv/lib/python3.6/site-packages/requests_toolbelt-0.9.1.dist-info/top_level.txt
venv/lib/python3.6/site-packages/six-1.15.0.dist-info/top_level.txt
venv/lib/python3.6/site-packages/tqdm-4.46.1.dist-info/entry_points.txt
venv/lib/python3.6/site-packages/tqdm-4.46.1.dist-info/top_level.txt
venv/lib/python3.6/site-packages/urllib3-1.25.9.dist-info/LICENSE.txt
venv/lib/python3.6/site-packages/urllib3-1.25.9.dist-info/top_level.txt
venv/lib/python3.6/site-packages/webencodings-0.5.1.dist-info/top_level.txt
venv/lib/python3.6/site-packages/wheel-0.34.2.dist-info/LICENSE.txt
venv/lib/python3.6/site-packages/wheel-0.34.2.dist-info/entry_points.txt
venv/lib/python3.6/site-packages/wheel-0.34.2.dist-info/top_level.txt
venv/lib/python3.6/site-packages/zipp-3.1.0.dist-info/top_level.txt