Metadata-Version: 1.1
Name: malekbasiccalculator
Version: 0.0.1
Summary: A very basic calculator
Home-page: UNKNOWN
Author: Malek Jaouadi
Author-email: UNKNOWN
License: MIT
Keywords: calculator
Platform: UNKNOWN
Classifier: Development Status :: 1 - Planning
Classifier: Intended Audience :: Education
Classifier: Operating System :: OS Independent
Classifier: License :: OSI Approved :: MIT License
Classifier: Programming Language :: Python :: 3
